rnaseqc/__init__.py
rnaseqc/__main__.py
rnaseqc/aggregate.py
rnaseqc/create_notebook.py
rnaseqc/insert_size_intervals.py
rnaseqc/legacy_exon_remap.py
rnaseqc/nb_encode.py
rnaseqc/plot.py
rnaseqc/report.py
rnaseqc/run.py
rnaseqc-0.0.3.dist-info/METADATA
rnaseqc-0.0.3.dist-info/WHEEL
rnaseqc-0.0.3.dist-info/top_level.txt
rnaseqc-0.0.3.dist-info/RECORD
