Metadata-Version: 2.1
Name: rnaseqc
Version: 0.0.3
Summary: Multi-sample visualization of metrics from RNA-SeQC
Classifier: Programming Language :: Python :: 3
Classifier: Intended Audience :: Science/Research
Classifier: Topic :: Scientific/Engineering :: Bio-Informatics
Requires-Dist: numpy
Requires-Dist: pandas
Requires-Dist: matplotlib
Requires-Dist: seaborn
Requires-Dist: qtl
Requires-Dist: agutil
Requires-Dist: nbformat
